LICENSE
README.md
setup.py
pysolardb/SolarDB.py
pysolardb/__init__.py
pysolardb.egg-info/PKG-INFO
pysolardb.egg-info/SOURCES.txt
pysolardb.egg-info/dependency_links.txt
pysolardb.egg-info/requires.txt
pysolardb.egg-info/top_level.txt
pysolardb/sample/__init__.py