Metadata-Version: 2.1
Name: pysolardb
Version: 0.3.0
Summary: Package used to access the LE2P solar database SolarDB
Home-page: https://github.com/LE2P/pysolardb
Author: Emmanuel Parfait
Author-email: manuparfait@gmail.com
License: MIT
Platform: UNKNOWN
Classifier: Development Status :: 4 - Beta
Classifier: Intended Audience :: Science/Research
Classifier: Intended Audience :: Education
Classifier: Intended Audience :: Developers
Classifier: License :: OSI Approved :: MIT License
Classifier: Natural Language :: English
Classifier: Operating System :: POSIX :: Linux
Classifier: Programming Language :: Python :: 3.8
Classifier: Topic :: Scientific/Engineering
License-File: LICENSE
